streamsx/hbase/__init__.py
streamsx/hbase/_hbase.py
streamsx/hbase/hbase-site.xml.template
streamsx.hbase-1.5.2.dist-info/DESCRIPTION.rst
streamsx.hbase-1.5.2.dist-info/LICENSE.txt
streamsx.hbase-1.5.2.dist-info/METADATA
streamsx.hbase-1.5.2.dist-info/RECORD
streamsx.hbase-1.5.2.dist-info/WHEEL
streamsx.hbase-1.5.2.dist-info/metadata.json
streamsx.hbase-1.5.2.dist-info/top_level.txt
